absolutely/__init__.py
absolutely-0.0.1.dist-info/LICENSE
absolutely-0.0.1.dist-info/METADATA
absolutely-0.0.1.dist-info/WHEEL
absolutely-0.0.1.dist-info/top_level.txt
absolutely-0.0.1.dist-info/RECORD
